ShenduXuexiJishuXuanxingBaipishu2018Nian/README.md
ShenduXuexiJishuXuanxingBaipishu2018Nian/__init__.py
ShenduXuexiJishuXuanxingBaipishu2018Nian/__main__.py
ShenduXuexiJishuXuanxingBaipishu2018Nian/file.pdf
ShenduXuexiJishuXuanxingBaipishu2018Nian/index.html
shendu_xuexi_jishu_xuanxing_baipishu_2018_nian-2024.3.3.0.dist-info/METADATA
shendu_xuexi_jishu_xuanxing_baipishu_2018_nian-2024.3.3.0.dist-info/WHEEL
shendu_xuexi_jishu_xuanxing_baipishu_2018_nian-2024.3.3.0.dist-info/entry_points.txt
shendu_xuexi_jishu_xuanxing_baipishu_2018_nian-2024.3.3.0.dist-info/top_level.txt
shendu_xuexi_jishu_xuanxing_baipishu_2018_nian-2024.3.3.0.dist-info/RECORD
